personalpasswords/__init__.py
personalpasswords/cli.py
personalpasswords-1.1.0.dist-info/METADATA
personalpasswords-1.1.0.dist-info/WHEEL
personalpasswords-1.1.0.dist-info/entry_points.txt
personalpasswords-1.1.0.dist-info/top_level.txt
personalpasswords-1.1.0.dist-info/RECORD
