Metadata-Version: 2.4
Name: personalpasswords
Version: 1.1.0
Summary: Generate personalized wordlists using OSINT data
Author: TangoMan222
Classifier: Programming Language :: Python :: 3
Classifier: License :: OSI Approved :: MIT License
Classifier: Operating System :: OS Independent
Requires-Python: >=3.6
Dynamic: author
Dynamic: classifier
Dynamic: requires-python
Dynamic: summary
